blender_mcp_vxai/__init__.py
blender_mcp_vxai/server.py
blender_mcp_vxai-1.0.7.dist-info/METADATA
blender_mcp_vxai-1.0.7.dist-info/WHEEL
blender_mcp_vxai-1.0.7.dist-info/entry_points.txt
blender_mcp_vxai-1.0.7.dist-info/licenses/LICENSE
blender_mcp_vxai-1.0.7.dist-info/RECORD
