Metadata-Version: 2.4
Name: blender-mcp-vxai
Version: 1.0.7
Summary: MCP server for Blender integration to enable dynamic 3D scene manipulation
Author-email: VxAI <vxasi7@gmail.com>
License: MIT
License-File: LICENSE
Requires-Python: >=3.7
Requires-Dist: mcp
